reaper_reapy_mcp/__init__.py
reaper_reapy_mcp/__main__.py
reaper_reapy_mcp/mcp_tools.py
reaper_reapy_mcp/reaper_controller.py
reaper_reapy_mcp/reaper_reapy_mcp.py
reaper_reapy_mcp/controllers/__init__.py
reaper_reapy_mcp/controllers/audio_controller.py
reaper_reapy_mcp/controllers/base_controller.py
reaper_reapy_mcp/controllers/fx_controller.py
reaper_reapy_mcp/controllers/marker_controller.py
reaper_reapy_mcp/controllers/master_controller.py
reaper_reapy_mcp/controllers/midi_controller.py
reaper_reapy_mcp/controllers/project_controller.py
reaper_reapy_mcp/controllers/track_controller.py
reaper_reapy_mcp/utils/__init__.py
reaper_reapy_mcp/utils/item_utils.py
reaper_reapy_mcp/utils/position_utils.py
reaper_reapy_mcp/utils/sample_audio.py
reaper_reapy_mcp-0.1.2.dist-info/METADATA
reaper_reapy_mcp-0.1.2.dist-info/WHEEL
reaper_reapy_mcp-0.1.2.dist-info/entry_points.txt
reaper_reapy_mcp-0.1.2.dist-info/top_level.txt
reaper_reapy_mcp-0.1.2.dist-info/RECORD
