Metadata-Version: 2.4
Name: reaper_reapy_mcp
Version: 0.1.2
Summary: REAPER DAW integration using MCP
Author-email: wegitor <your.email@example.com>
License: MIT
Project-URL: Homepage, https://github.com/wegitor/reaper-reapy-mcp
Project-URL: Repository, https://github.com/wegitor/reaper-reapy-mcp.git
Project-URL: Issues, https://github.com/wegitor/reaper-reapy-mcp/issues
Classifier: Development Status :: 3 - Alpha
Classifier: Intended Audience :: Developers
Classifier: License :: OSI Approved :: MIT License
Classifier: Programming Language :: Python :: 3
Classifier: Programming Language :: Python :: 3.10
Classifier: Programming Language :: Python :: 3.11
Classifier: Programming Language :: Python :: 3.12
Requires-Python: >=3.10
Requires-Dist: python-reapy>=0.9.0
Requires-Dist: python-osc>=1.8.0
Requires-Dist: pytest>=7.0.0
Requires-Dist: mcp[cli]>=0.1.0
Requires-Dist: python-dotenv>=1.0.0
Requires-Dist: requests>=2.31.0
